{
  "compare" : null,
  "previous_successful_build" : {
    "build_num" : 61,
    "status" : "success",
    "build_time_millis" : 873222
  },
  "build_parameters" : {
    "CIRCLE_JOB" : "process-and-publish"
  },
  "oss" : true,
  "all_commit_details_truncated" : false,
  "committer_date" : "2019-06-20T10:42:58+02:00",
  "steps" : [ {
    "name" : "Spin up Environment",
    "actions" : [ {
      "truncated" : false,
      "index" : 0,
      "parallel" : true,
      "failed" : null,
      "infrastructure_fail" : null,
      "name" : "Spin up Environment",
      "bash_command" : null,
      "status" : "success",
      "timedout" : null,
      "continue" : null,
      "end_time" : "2019-06-20T08:43:26.638Z",
      "type" : "test",
      "allocation_id" : "5d0b471f03847e0008cbf06e-0-build/23EDEDDA",
      "output_url" : "https://circle-production-action-output.s3.amazonaws.com/08e94a10006499065274b0d5-5cb96bfb03c6cb00010e1586-0-0?X-Amz-Algorithm=AWS4-HMAC-SHA256&X-Amz-Date=20200216T144122Z&X-Amz-SignedHeaders=host&X-Amz-Expires=432000&X-Amz-Credential=AKIAIJNI6FA5RIAFFQ7Q%2F20200216%2Fus-east-1%2Fs3%2Faws4_request&X-Amz-Signature=b6735bed2b8f05c74c8b28877edda631ee1952043f0903c903e4be8ddf0cf345",
      "start_time" : "2019-06-20T08:43:17.831Z",
      "background" : false,
      "exit_code" : null,
      "insignificant" : false,
      "canceled" : null,
      "step" : 0,
      "run_time_millis" : 8807,
      "has_output" : true
    } ]
  }, {
    "name" : "Récupération de decp-rama",
    "actions" : [ {
      "truncated" : false,
      "index" : 0,
      "parallel" : true,
      "failed" : null,
      "infrastructure_fail" : null,
      "name" : "Récupération de decp-rama",
      "bash_command" : "#!/bin/bash -eo pipefail\nmkdir -p /home/circleci/project\ncd /home/circleci/project\ngit clone https://github.com/etalab/decp-rama\ncd decp-rama\ngit checkout $CIRCLE_BRANCH\n",
      "status" : "success",
      "timedout" : null,
      "continue" : null,
      "end_time" : "2019-06-20T08:43:27.094Z",
      "type" : "test",
      "allocation_id" : "5d0b471f03847e0008cbf06e-0-build/23EDEDDA",
      "output_url" : "https://circle-production-action-output.s3.amazonaws.com/9fe94a1000649906e274b0d5-5cb96bfb03c6cb00010e1586-101-0?X-Amz-Algorithm=AWS4-HMAC-SHA256&X-Amz-Date=20200216T144122Z&X-Amz-SignedHeaders=host&X-Amz-Expires=432000&X-Amz-Credential=AKIAIJNI6FA5RIAFFQ7Q%2F20200216%2Fus-east-1%2Fs3%2Faws4_request&X-Amz-Signature=569939921fc6902d8396e7f6b5797e2db8260688082589d156faedd8e8fe830d",
      "start_time" : "2019-06-20T08:43:26.756Z",
      "background" : false,
      "exit_code" : 0,
      "insignificant" : false,
      "canceled" : null,
      "step" : 101,
      "run_time_millis" : 338,
      "has_output" : true
    } ]
  }, {
    "name" : "Récupération et traitement des données",
    "actions" : [ {
      "truncated" : false,
      "index" : 0,
      "parallel" : true,
      "failed" : null,
      "infrastructure_fail" : null,
      "name" : "Récupération et traitement des données",
      "bash_command" : "#!/bin/bash -eo pipefail\ncd /home/circleci/project/decp-rama\n./process.sh all package sequence\n",
      "status" : "success",
      "timedout" : null,
      "continue" : null,
      "end_time" : "2019-06-20T08:59:45.749Z",
      "type" : "test",
      "allocation_id" : "5d0b471f03847e0008cbf06e-0-build/23EDEDDA",
      "output_url" : "https://circle-production-action-output.s3.amazonaws.com/ffe94a1000649906f274b0d5-5cb96bfb03c6cb00010e1586-102-0?X-Amz-Algorithm=AWS4-HMAC-SHA256&X-Amz-Date=20200216T144122Z&X-Amz-SignedHeaders=host&X-Amz-Expires=432000&X-Amz-Credential=AKIAIJNI6FA5RIAFFQ7Q%2F20200216%2Fus-east-1%2Fs3%2Faws4_request&X-Amz-Signature=14633f9f942ba74ceb507fed4efbdf2ba48227474b24fc4ca48ea4d04db42019",
      "start_time" : "2019-06-20T08:43:27.098Z",
      "background" : false,
      "exit_code" : 0,
      "insignificant" : false,
      "canceled" : null,
      "step" : 102,
      "run_time_millis" : 978651,
      "has_output" : true
    } ]
  }, {
    "name" : "Publication des données sur (next.)data.gouv.fr",
    "actions" : [ {
      "truncated" : false,
      "index" : 0,
      "parallel" : true,
      "failed" : null,
      "infrastructure_fail" : null,
      "name" : "Publication des données sur (next.)data.gouv.fr",
      "bash_command" : "#!/bin/bash -eo pipefail\ncd /home/circleci/project/decp-rama\n./publish.sh\n",
      "status" : "success",
      "timedout" : null,
      "continue" : null,
      "end_time" : "2019-06-20T08:59:45.761Z",
      "type" : "test",
      "allocation_id" : "5d0b471f03847e0008cbf06e-0-build/23EDEDDA",
      "start_time" : "2019-06-20T08:59:45.753Z",
      "background" : false,
      "exit_code" : 0,
      "insignificant" : false,
      "canceled" : null,
      "step" : 103,
      "run_time_millis" : 8,
      "has_output" : false
    } ]
  } ],
  "body" : "Et les doublons sont calculés en amont dans merge_all_sources.sh (92f43a895)",
  "usage_queued_at" : "2019-06-20T08:43:11.371Z",
  "context_ids" : [ ],
  "fail_reason" : null,
  "retry_of" : null,
  "reponame" : "decp-rama",
  "ssh_users" : [ ],
  "build_url" : "https://circleci.com/gh/etalab/decp-rama/76",
  "parallel" : 1,
  "failed" : false,
  "branch" : "develop",
  "username" : "etalab",
  "author_date" : "2019-06-20T10:42:58+02:00",
  "why" : "github",
  "user" : {
    "is_user" : true,
    "login" : "ColinMaudry",
    "avatar_url" : "https://avatars0.githubusercontent.com/u/3747136?v=4",
    "name" : "Colin Maudry",
    "vcs_type" : "github",
    "id" : 3747136
  },
  "vcs_revision" : "3087e3debba634cf132ba2a053e5ef7d7e7d5bfe",
  "workflows" : {
    "job_name" : "process-and-publish",
    "job_id" : "05966881-f84e-4092-a7f0-13fbea67d6ec",
    "workflow_id" : "3819a6cb-dae4-4cb3-916a-80bc1577e94c",
    "workspace_id" : "3819a6cb-dae4-4cb3-916a-80bc1577e94c",
    "upstream_job_ids" : [ ],
    "upstream_concurrency_map" : { },
    "workflow_name" : "dev"
  },
  "owners" : [ "ColinMaudry" ],
  "vcs_tag" : null,
  "pull_requests" : [ ],
  "build_num" : 76,
  "infrastructure_fail" : false,
  "committer_email" : "colin@maudry.com",
  "has_artifacts" : true,
  "previous" : {
    "build_num" : 74,
    "status" : "failed",
    "build_time_millis" : 1876916
  },
  "status" : "success",
  "committer_name" : "Colin Maudry",
  "retries" : null,
  "subject" : "La boucle for utilise maintenant le vrai nombre de ligne de todaysMarches #16",
  "vcs_type" : "github",
  "timedout" : false,
  "dont_build" : null,
  "lifecycle" : "finished",
  "no_dependency_cache" : false,
  "stop_time" : "2019-06-20T08:59:45.797Z",
  "ssh_disabled" : true,
  "build_time_millis" : 988012,
  "picard" : {
    "build_agent" : {
      "image" : "circleci/picard:1.0.11727-b0960fc9",
      "properties" : {
        "build_agent" : "1.0.11727-b0960fc9",
        "executor" : "docker"
      }
    },
    "resource_class" : {
      "cpu" : 2.0,
      "ram" : 4096,
      "class" : "medium"
    },
    "executor" : "docker"
  },
  "circle_yml" : {
    "string" : "version: 2\njobs:\n  process-and-publish:\n    docker:\n    - image: etalab/decp-rama\n    steps:\n    - run:\n        name: Récupération de decp-rama\n        command: |\n          mkdir -p /home/circleci/project\n          cd /home/circleci/project\n          git clone https://github.com/etalab/decp-rama\n          cd decp-rama\n          git checkout $CIRCLE_BRANCH\n    - run:\n        name: Récupération et traitement des données\n        command: |\n          cd /home/circleci/project/decp-rama\n          ./process.sh all package sequence\n    - run:\n        name: Publication des données sur (next.)data.gouv.fr\n        command: |\n          cd /home/circleci/project/decp-rama\n          ./publish.sh\nworkflows:\n  version: 2\n  dev:\n    jobs:\n    - process-and-publish:\n        filters:\n          branches:\n            only:\n            - develop\n  daily:\n    jobs:\n    - process-and-publish\n    triggers:\n    - schedule:\n        cron: 0 4 * * 2,3,4,5,6\n        filters:\n          branches:\n            only:\n            - master\n"
  },
  "messages" : [ ],
  "is_first_green_build" : false,
  "job_name" : null,
  "start_time" : "2019-06-20T08:43:17.785Z",
  "canceler" : null,
  "all_commit_details" : [ {
    "committer_date" : "2019-06-20T10:39:05+02:00",
    "body" : "",
    "branch" : "develop",
    "author_date" : "2019-06-20T10:39:05+02:00",
    "committer_email" : "colin@maudry.com",
    "commit" : "92f43a895c6e4aa1b1a20d9c2befe8018da1367c",
    "committer_login" : "ColinMaudry",
    "committer_name" : "Colin Maudry",
    "subject" : "Affiche du nombre de doublons détectés dans le decp.json produit.",
    "commit_url" : "https://github.com/etalab/decp-rama/commit/92f43a895c6e4aa1b1a20d9c2befe8018da1367c",
    "author_login" : "ColinMaudry",
    "author_name" : "Colin Maudry",
    "author_email" : "colin@maudry.com"
  }, {
    "committer_date" : "2019-06-20T10:42:58+02:00",
    "body" : "Et les doublons sont calculés en amont dans merge_all_sources.sh (92f43a895)",
    "branch" : "develop",
    "author_date" : "2019-06-20T10:42:58+02:00",
    "committer_email" : "colin@maudry.com",
    "commit" : "3087e3debba634cf132ba2a053e5ef7d7e7d5bfe",
    "committer_login" : "ColinMaudry",
    "committer_name" : "Colin Maudry",
    "subject" : "La boucle for utilise maintenant le vrai nombre de ligne de todaysMarches #16",
    "commit_url" : "https://github.com/etalab/decp-rama/commit/3087e3debba634cf132ba2a053e5ef7d7e7d5bfe",
    "author_login" : "ColinMaudry",
    "author_name" : "Colin Maudry",
    "author_email" : "colin@maudry.com"
  } ],
  "platform" : "2.0",
  "outcome" : "success",
  "vcs_url" : "https://github.com/etalab/decp-rama",
  "author_name" : "Colin Maudry",
  "node" : null,
  "queued_at" : "2019-06-20T08:43:11.427Z",
  "canceled" : false,
  "author_email" : "colin@maudry.com"
}